{
  "required": true,
  "minVersion": "0.8",
  "package": "com.maxsters.realtimeminecraftcorruptionsimulator.mixin",
  "compatibilityLevel": "JAVA_17",
  "mixins": [
    "BoatFluidStateMixin",
    "ChunkGeneratorMixin",
    "ClimateSamplerMixin",
    "ConfiguredWorldCarverMixin",
    "EntityAttackableMixin",
    "EntityCollisionMixin",
    "EntityFluidStateMixin",
    "FeatureMixin",
    "LivingEntityTargetingMixin",
    "NoiseRouterMixin",
    "PathNavigationMixin",
    "PlayerMechanicsMixin",
    "SurfaceRulesStateRuleMixin"
  ],
  "client": [
    "client.AbstractSliderButtonMixin",
    "client.AmbientOcclusionFaceMixin",
    "client.BiomeColorsMixin",
    "client.BlockEntityRenderDispatcherMixin",
    "client.BoatRendererMixin",
    "client.EntityRenderDispatcherMixin",
    "client.FontStringRenderOutputMixin",
    "client.LevelRendererMixin",
    "client.LightTextureMixin",
    "client.LiquidBlockRendererMixin",
    "client.LivingEntityRendererMixin",
    "client.ModelBlockRendererMixin",
    "client.ModelPartMixin",
    "client.OptionInstanceMixin",
    "client.ParticleMixin",
    "client.SheetedDecalTextureGeneratorMixin",
    "client.SimpleBakedModelMixin",
    "client.TerrainParticleMixin"
  ],
  "injectors": {
    "defaultRequire": 0
  }
}
